AUTHORS.rst
CONTRIBUTING.rst
MANIFEST.in
README.rst
pytest.ini
requirements.txt
setup.py
tox.ini
nekrobox/__init__.py
nekrobox/docdecs.py
nekrobox/nekrobox.py
nekrobox/output.py
nekrobox/path.py
nekrobox/temp.py
nekrobox/tree.py
nekrobox.egg-info/PKG-INFO
nekrobox.egg-info/SOURCES.txt
nekrobox.egg-info/dependency_links.txt
nekrobox.egg-info/not-zip-safe
nekrobox.egg-info/top_level.txt
test/test_docdecs.py
test/test_nekrobox.py
test/test_path.py
test/test_tree.py