Metadata-Version: 1.1
Name: nekrobox
Version: 0.6.0
Summary: A utilities library by Nekroze.
Home-page: https://lab.nekroze.com/tlawson/nekrobox
Author: Taylor "Nekroze" Lawson
Author-email: tlawson@nekroze.com
License: MIT
Keywords: nekrobox
Platform: UNKNOWN
Classifier: Development Status :: 2 - Pre-Alpha
Classifier: Intended Audience :: Developers
Classifier: License :: OSI Approved :: MIT License
Classifier: Natural Language :: English
Classifier: Programming Language :: Python :: 2
Classifier: Programming Language :: Python :: 2.7
Classifier: Programming Language :: Python :: 2.6
Classifier: Programming Language :: Python :: 3
Classifier: Programming Language :: Python :: 3.3
